MANIFEST.in
README.rst
setup.cfg
setup.py
docs/.gitignore
docs/HISTORY.txt
docs/LICENSE.GPL
docs/LICENSE.txt
docs/source/HISTORY.rst
docs/source/api.rst
docs/source/api_browser.rst
docs/source/api_exceptions.rst
docs/source/api_nodes_forms.rst
docs/source/api_pages.rst
docs/source/conf.py
docs/source/index.rst
docs/source/introduction.rst
docs/source/quickstart.rst
docs/source/userdoc.rst
ftw/__init__.py
ftw.testbrowser.egg-info/PKG-INFO
ftw.testbrowser.egg-info/SOURCES.txt
ftw.testbrowser.egg-info/dependency_links.txt
ftw.testbrowser.egg-info/entry_points.txt
ftw.testbrowser.egg-info/namespace_packages.txt
ftw.testbrowser.egg-info/not-zip-safe
ftw.testbrowser.egg-info/requires.txt
ftw.testbrowser.egg-info/top_level.txt
ftw/testbrowser/__init__.py
ftw/testbrowser/compat.py
ftw/testbrowser/core.py
ftw/testbrowser/exceptions.py
ftw/testbrowser/form.py
ftw/testbrowser/interfaces.py
ftw/testbrowser/log.py
ftw/testbrowser/nodes.py
ftw/testbrowser/parser.py
ftw/testbrowser/plone5.py
ftw/testbrowser/queryinfo.py
ftw/testbrowser/table.py
ftw/testbrowser/testing.py
ftw/testbrowser/utils.py
ftw/testbrowser/drivers/__init__.py
ftw/testbrowser/drivers/layers.py
ftw/testbrowser/drivers/mechdriver.py
ftw/testbrowser/drivers/requestsdriver.py
ftw/testbrowser/drivers/staticdriver.py
ftw/testbrowser/drivers/traversaldriver.py
ftw/testbrowser/drivers/utils.py
ftw/testbrowser/drivers/webtest.py
ftw/testbrowser/pages/__init__.py
ftw/testbrowser/pages/dexterity.py
ftw/testbrowser/pages/editbar.py
ftw/testbrowser/pages/factoriesmenu.py
ftw/testbrowser/pages/folder_contents.py
ftw/testbrowser/pages/plone.py
ftw/testbrowser/pages/statusmessages.py
ftw/testbrowser/pages/z3cform.py
ftw/testbrowser/tests/__init__.py
ftw/testbrowser/tests/alldrivers.py
ftw/testbrowser/tests/helpers.py
ftw/testbrowser/tests/interfaces.py
ftw/testbrowser/tests/test_browser.py
ftw/testbrowser/tests/test_context.py
ftw/testbrowser/tests/test_cookies.py
ftw/testbrowser/tests/test_defaultdriver.py
ftw/testbrowser/tests/test_dexterity_forms.py
ftw/testbrowser/tests/test_driver_layers.py
ftw/testbrowser/tests/test_driver_utils.py
ftw/testbrowser/tests/test_drivers_mechdriver.py
ftw/testbrowser/tests/test_drivers_requestsdriver.py
ftw/testbrowser/tests/test_drivers_staticdriver.py
ftw/testbrowser/tests/test_drivers_traversaldriver.py
