Metadata-Version: 2.1
Name: ftw.testbrowser
Version: 2.1.2
Summary: A test browser for Zope and Plone.
Home-page: https://github.com/4teamwork/ftw.testbrowser
Author: 4teamwork AG
Author-email: mailto:info@4teamwork.ch
License: GPL2
Keywords: ftw browser testbrowser test
Platform: UNKNOWN
Classifier: Framework :: Plone
Classifier: Framework :: Plone :: 4.3
Classifier: Framework :: Plone :: 5.1
Classifier: Framework :: Plone :: 5.2
Classifier: Programming Language :: Python
Classifier: Programming Language :: Python :: 2.7
Classifier: Programming Language :: Python :: 3.7
Classifier: Intended Audience :: Developers
Classifier: Topic :: Software Development :: Libraries :: Python Modules
Provides-Extra: tests
Provides-Extra: zope2
Provides-Extra: tests_plone4
Provides-Extra: plone
